[
    {
        "title": "अतुल परचुरे",
        "link": "https://trends.google.com/trends/trendingsearches/daily?geo=IN#%E0%A4%85%E0%A4%A4%E0%A5%81%E0%A4%B2%20%E0%A4%AA%E0%A4%B0%E0%A4%9A%E0%A5%81%E0%A4%B0%E0%A5%87",
        "pubdate": "Tue, 15 Oct 2024 01:30:00 +0530"
    },
    {
        "title": "FA Cup draw",
        "link": "https://trends.google.com/trends/trendingsearches/daily?geo=GB#FA%20Cup%20draw",
        "pubdate": "Mon, 14 Oct 2024 20:00:00 +0100"
    },
    {
        "title": "實惠",
        "link": "https://trends.google.com/trends/trendingsearches/daily?geo=HK#%E5%AF%A6%E6%83%A0",
        "pubdate": "Tue, 15 Oct 2024 01:00:00 +0800"
    },
    {
        "title": "Deutschland – Niederlande",
        "link": "https://trends.google.com/trends/trendingsearches/daily?geo=DE#Deutschland%20%E2%80%93%20Niederlande",
        "pubdate": "Mon, 14 Oct 2024 15:00:00 +0200"
    },
    {
        "title": "TF1",
        "link": "https://trends.google.com/trends/trendingsearches/daily?geo=FR#TF1",
        "pubdate": "Tue, 15 Oct 2024 01:00:00 +0200"
    },
    {
        "title": "山本太郎",
        "link": "https://trends.google.com/trends/trendingsearches/daily?geo=JP#%E5%B1%B1%E6%9C%AC%E5%A4%AA%E9%83%8E",
        "pubdate": "Tue, 15 Oct 2024 07:00:00 +0900"
    },
    {
        "title": "Maxx Crosby",
        "link": "https://trends.google.com/trends/trendingsearches/daily?geo=US#Maxx%20Crosby",
        "pubdate": "Mon, 14 Oct 2024 13:00:00 -0700"
    },
    {
        "title": "Налог на бездетность",
        "link": "https://trends.google.com/trends/trendingsearches/daily?geo=RU#%D0%9D%D0%B0%D0%BB%D0%BE%D0%B3%20%D0%BD%D0%B0%20%D0%B1%D0%B5%D0%B7%D0%B4%D0%B5%D1%82%D0%BD%D0%BE%D1%81%D1%82%D1%8C",
        "pubdate": "Tue, 15 Oct 2024 00:00:00 +0300"
    },
    {
        "title": "Typhlosion",
        "link": "https://trends.google.com/trends/trendingsearches/daily?geo=PH#Typhlosion",
        "pubdate": "Tue, 15 Oct 2024 01:00:00 +0800"
    },
    {
        "title": "Vortex",
        "link": "https://trends.google.com/trends/trendingsearches/daily?geo=CZ#Vortex",
        "pubdate": "Tue, 15 Oct 2024 01:00:00 +0200"
    },
    {
        "title": "蟑螂",
        "link": "https://trends.google.com/trends/trendingsearches/daily?geo=TW#%E8%9F%91%E8%9E%82",
        "pubdate": "Tue, 15 Oct 2024 00:00:00 +0800"
    },
    {
        "title": "Γιαννακοπουλου",
        "link": "https://trends.google.com/trends/trendingsearches/daily?geo=GR#%CE%93%CE%B9%CE%B1%CE%BD%CE%BD%CE%B1%CE%BA%CE%BF%CF%80%CE%BF%CF%85%CE%BB%CE%BF%CF%85",
        "pubdate": "Tue, 15 Oct 2024 01:00:00 +0300"
    },
    {
        "title": "Mets vs Dodgers",
        "link": "https://trends.google.com/trends/trendingsearches/daily?geo=CA#Mets%20vs%20Dodgers",
        "pubdate": "Mon, 14 Oct 2024 00:00:00 -0400"
    },
    {
        "title": "איתי תורג'מן",
        "link": "https://trends.google.com/trends/trendingsearches/daily?geo=IL#%D7%90%D7%99%D7%AA%D7%99%20%D7%AA%D7%95%D7%A8%D7%92'%D7%9E%D7%9F",
        "pubdate": "Tue, 15 Oct 2024 00:00:00 +0300"
    },
    {
        "title": "Patriotas  Santa Fe",
        "link": "https://trends.google.com/trends/trendingsearches/daily?geo=CO#Patriotas%20%20Santa%20Fe",
        "pubdate": "Mon, 14 Oct 2024 14:00:00 -0500"
    },
    {
        "title": "Belgium vs France",
        "link": "https://trends.google.com/trends/trendingsearches/daily?geo=AU#Belgium%20vs%20France",
        "pubdate": "Tue, 15 Oct 2024 08:00:00 +1100"
    },
    {
        "title": "Chile vs Colombia",
        "link": "https://trends.google.com/trends/trendingsearches/daily?geo=CL#Chile%20vs%20Colombia",
        "pubdate": "Mon, 14 Oct 2024 12:00:00 -0300"
    },
    {
        "title": "Germany vs Netherlands",
        "link": "https://trends.google.com/trends/trendingsearches/daily?geo=ZA#Germany%20vs%20Netherlands",
        "pubdate": "Mon, 14 Oct 2024 18:00:00 +0200"
    },
    {
        "title": "Tajemnicza Monika",
        "link": "https://trends.google.com/trends/trendingsearches/daily?geo=PL#Tajemnicza%20Monika",
        "pubdate": "Mon, 14 Oct 2024 14:00:00 +0200"
    },
    {
        "title": "New Zealand Women vs Pakistan Women",
        "link": "https://trends.google.com/trends/trendingsearches/daily?geo=NZ#New%20Zealand%20Women%20vs%20Pakistan%20Women",
        "pubdate": "Tue, 15 Oct 2024 07:00:00 +1300"
    }
]