[
    {
        "title": "Starship",
        "link": "https://trends.google.com/trends/trendingsearches/daily?geo=FR#Starship",
        "pubdate": "Wed, 20 Nov 2024 02:00:00 +0100"
    },
    {
        "title": "林夏薇",
        "link": "https://trends.google.com/trends/trendingsearches/daily?geo=HK#%E6%9E%97%E5%A4%8F%E8%96%87",
        "pubdate": "Wed, 20 Nov 2024 00:00:00 +0800"
    },
    {
        "title": "年末ジャンボ",
        "link": "https://trends.google.com/trends/trendingsearches/daily?geo=JP#%E5%B9%B4%E6%9C%AB%E3%82%B8%E3%83%A3%E3%83%B3%E3%83%9C",
        "pubdate": "Wed, 20 Nov 2024 15:00:00 +0900"
    },
    {
        "title": "Argentina vs Peru",
        "link": "https://trends.google.com/trends/trendingsearches/daily?geo=GB#Argentina%20vs%20Peru",
        "pubdate": "Wed, 20 Nov 2024 04:00:00 +0000"
    },
    {
        "title": "Linda McMahon Education",
        "link": "https://trends.google.com/trends/trendingsearches/daily?geo=US#Linda%20McMahon%20Education",
        "pubdate": "Wed, 20 Nov 2024 00:00:00 -0800"
    },
    {
        "title": "Brazil vs Uruguay",
        "link": "https://trends.google.com/trends/trendingsearches/daily?geo=IN#Brazil%20vs%20Uruguay",
        "pubdate": "Wed, 20 Nov 2024 06:30:00 +0530"
    },
    {
        "title": "S.T.A.L.K.E.R. 2",
        "link": "https://trends.google.com/trends/trendingsearches/daily?geo=RU#S.T.A.L.K.E.R.%202",
        "pubdate": "Wed, 20 Nov 2024 11:00:00 +0300"
    },
    {
        "title": "Buß- und Bettag",
        "link": "https://trends.google.com/trends/trendingsearches/daily?geo=DE#Bu%C3%9F-%20und%20Bettag",
        "pubdate": "Wed, 20 Nov 2024 08:00:00 +0100"
    },
    {
        "title": "Lakers  Jazz",
        "link": "https://trends.google.com/trends/trendingsearches/daily?geo=MX#Lakers%20%20Jazz",
        "pubdate": "Wed, 20 Nov 2024 00:00:00 -0600"
    },
    {
        "title": "陳傑憲",
        "link": "https://trends.google.com/trends/trendingsearches/daily?geo=TW#%E9%99%B3%E5%82%91%E6%86%B2",
        "pubdate": "Wed, 20 Nov 2024 01:00:00 +0800"
    },
    {
        "title": "Wicked",
        "link": "https://trends.google.com/trends/trendingsearches/daily?geo=NZ#Wicked",
        "pubdate": "Wed, 20 Nov 2024 21:00:00 +1300"
    },
    {
        "title": "ATACMS",
        "link": "https://trends.google.com/trends/trendingsearches/daily?geo=CZ#ATACMS",
        "pubdate": "Wed, 20 Nov 2024 08:00:00 +0100"
    },
    {
        "title": "O Boticário",
        "link": "https://trends.google.com/trends/trendingsearches/daily?geo=BR#O%20Botic%C3%A1rio",
        "pubdate": "Wed, 20 Nov 2024 02:00:00 -0500"
    },
    {
        "title": "Maçkolik",
        "link": "https://trends.google.com/trends/trendingsearches/daily?geo=TR#Ma%C3%A7kolik",
        "pubdate": "Wed, 20 Nov 2024 01:00:00 +0300"
    },
    {
        "title": "Wiener Linien",
        "link": "https://trends.google.com/trends/trendingsearches/daily?geo=AT#Wiener%20Linien",
        "pubdate": "Wed, 20 Nov 2024 07:00:00 +0100"
    },
    {
        "title": "Argentina  Perù",
        "link": "https://trends.google.com/trends/trendingsearches/daily?geo=IT#Argentina%20%20Per%C3%B9",
        "pubdate": "Wed, 20 Nov 2024 02:00:00 +0100"
    },
    {
        "title": "Stalker 2",
        "link": "https://trends.google.com/trends/trendingsearches/daily?geo=FI#Stalker%202",
        "pubdate": "Wed, 20 Nov 2024 08:00:00 +0200"
    },
    {
        "title": "MagisTV",
        "link": "https://trends.google.com/trends/trendingsearches/daily?geo=AR#MagisTV",
        "pubdate": "Wed, 20 Nov 2024 05:00:00 -0300"
    },
    {
        "title": "Microsoft Flight Simulator 2024",
        "link": "https://trends.google.com/trends/trendingsearches/daily?geo=CH#Microsoft%20Flight%20Simulator%202024",
        "pubdate": "Wed, 20 Nov 2024 09:00:00 +0100"
    },
    {
        "title": "Slub od pierwszego wejrzenia",
        "link": "https://trends.google.com/trends/trendingsearches/daily?geo=PL#Slub%20od%20pierwszego%20wejrzenia",
        "pubdate": "Wed, 20 Nov 2024 00:00:00 +0100"
    }
]