[
    {
        "title": "Xavier Niel",
        "link": "https://trends.google.com/trends/trendingsearches/daily?geo=FR#Xavier%20Niel",
        "pubdate": "Tue, 01 Oct 2024 10:00:00 +0200"
    },
    {
        "title": "Champions League",
        "link": "https://trends.google.com/trends/trendingsearches/daily?geo=DE#Champions%20League",
        "pubdate": "Tue, 01 Oct 2024 09:00:00 +0200"
    },
    {
        "title": "Вячеслав Добрынин",
        "link": "https://trends.google.com/trends/trendingsearches/daily?geo=RU#%D0%92%D1%8F%D1%87%D0%B5%D1%81%D0%BB%D0%B0%D0%B2%20%D0%94%D0%BE%D0%B1%D1%80%D1%8B%D0%BD%D0%B8%D0%BD",
        "pubdate": "Tue, 01 Oct 2024 13:00:00 +0300"
    },
    {
        "title": "電影",
        "link": "https://trends.google.com/trends/trendingsearches/daily?geo=HK#%E9%9B%BB%E5%BD%B1",
        "pubdate": "Tue, 01 Oct 2024 16:00:00 +0800"
    },
    {
        "title": "Govinda",
        "link": "https://trends.google.com/trends/trendingsearches/daily?geo=IN#Govinda",
        "pubdate": "Tue, 01 Oct 2024 10:30:00 +0530"
    },
    {
        "title": "Thelwall Viaduct",
        "link": "https://trends.google.com/trends/trendingsearches/daily?geo=GB#Thelwall%20Viaduct",
        "pubdate": "Tue, 01 Oct 2024 00:00:00 +0100"
    },
    {
        "title": "台風気象情報、台風第17号",
        "link": "https://trends.google.com/trends/trendingsearches/daily?geo=JP#%E5%8F%B0%E9%A2%A8%E6%B0%97%E8%B1%A1%E6%83%85%E5%A0%B1%E3%80%81%E5%8F%B0%E9%A2%A8%E7%AC%AC17%E5%8F%B7",
        "pubdate": "Tue, 01 Oct 2024 11:00:00 +0900"
    },
    {
        "title": "Ken Page",
        "link": "https://trends.google.com/trends/trendingsearches/daily?geo=US#Ken%20Page",
        "pubdate": "Tue, 01 Oct 2024 06:00:00 -0700"
    },
    {
        "title": "Dia do vendedor",
        "link": "https://trends.google.com/trends/trendingsearches/daily?geo=BR#Dia%20do%20vendedor",
        "pubdate": "Tue, 01 Oct 2024 05:00:00 -0500"
    },
    {
        "title": "Silence 4",
        "link": "https://trends.google.com/trends/trendingsearches/daily?geo=PT#Silence%204",
        "pubdate": "Tue, 01 Oct 2024 11:00:00 +0100"
    },
    {
        "title": "Mutombo",
        "link": "https://trends.google.com/trends/trendingsearches/daily?geo=TW#Mutombo",
        "pubdate": "Tue, 01 Oct 2024 00:00:00 +0800"
    },
    {
        "title": "Jimmy Carter",
        "link": "https://trends.google.com/trends/trendingsearches/daily?geo=DK#Jimmy%20Carter",
        "pubdate": "Tue, 01 Oct 2024 07:00:00 +0200"
    },
    {
        "title": "Marwah Rizqy",
        "link": "https://trends.google.com/trends/trendingsearches/daily?geo=CA#Marwah%20Rizqy",
        "pubdate": "Tue, 01 Oct 2024 10:00:00 -0400"
    },
    {
        "title": "Temperatura bogota",
        "link": "https://trends.google.com/trends/trendingsearches/daily?geo=CO#Temperatura%20bogota",
        "pubdate": "Tue, 01 Oct 2024 05:00:00 -0500"
    },
    {
        "title": "Champions",
        "link": "https://trends.google.com/trends/trendingsearches/daily?geo=CL#Champions",
        "pubdate": "Tue, 01 Oct 2024 11:00:00 -0300"
    },
    {
        "title": "Ariana Grande",
        "link": "https://trends.google.com/trends/trendingsearches/daily?geo=AU#Ariana%20Grande",
        "pubdate": "Wed, 02 Oct 2024 00:00:00 +1000"
    },
    {
        "title": "1 октября праздник",
        "link": "https://trends.google.com/trends/trendingsearches/daily?geo=UA#1%20%D0%BE%D0%BA%D1%82%D1%8F%D0%B1%D1%80%D1%8F%20%D0%BF%D1%80%D0%B0%D0%B7%D0%B4%D0%BD%D0%B8%D0%BA",
        "pubdate": "Tue, 01 Oct 2024 05:00:00 +0300"
    },
    {
        "title": "Dikembe Mutombo",
        "link": "https://trends.google.com/trends/trendingsearches/daily?geo=PH#Dikembe%20Mutombo",
        "pubdate": "Tue, 01 Oct 2024 00:00:00 +0800"
    },
    {
        "title": "Klasemen Al-Nassr vs Al Rayyan",
        "link": "https://trends.google.com/trends/trendingsearches/daily?geo=ID#Klasemen%20Al-Nassr%20vs%20Al%20Rayyan",
        "pubdate": "Tue, 01 Oct 2024 01:00:00 +0700"
    },
    {
        "title": "Zene világnapja",
        "link": "https://trends.google.com/trends/trendingsearches/daily?geo=HU#Zene%20vil%C3%A1gnapja",
        "pubdate": "Tue, 01 Oct 2024 06:00:00 +0200"
    }
]