[
    {
        "title": "Manchester United",
        "link": "https://trends.google.com/trends/trendingsearches/daily?geo=IN#Manchester%20United",
        "pubdate": "Fri, 04 Oct 2024 06:30:00 +0530"
    },
    {
        "title": "Beşiktaş – Eintracht Frankfurt",
        "link": "https://trends.google.com/trends/trendingsearches/daily?geo=DE#Be%C5%9Fikta%C5%9F%20%E2%80%93%20Eintracht%20Frankfurt",
        "pubdate": "Thu, 03 Oct 2024 21:00:00 +0200"
    },
    {
        "title": "山崎晃大朗",
        "link": "https://trends.google.com/trends/trendingsearches/daily?geo=JP#%E5%B1%B1%E5%B4%8E%E6%99%83%E5%A4%A7%E6%9C%97",
        "pubdate": "Fri, 04 Oct 2024 14:00:00 +0900"
    },
    {
        "title": "Chelsea",
        "link": "https://trends.google.com/trends/trendingsearches/daily?geo=GB#Chelsea",
        "pubdate": "Thu, 03 Oct 2024 20:00:00 +0100"
    },
    {
        "title": "Taiwan",
        "link": "https://trends.google.com/trends/trendingsearches/daily?geo=FR#Taiwan",
        "pubdate": "Fri, 04 Oct 2024 06:00:00 +0200"
    },
    {
        "title": "Buccaneers vs Falcons",
        "link": "https://trends.google.com/trends/trendingsearches/daily?geo=US#Buccaneers%20vs%20Falcons",
        "pubdate": "Thu, 03 Oct 2024 12:00:00 -0700"
    },
    {
        "title": "波圖 對曼聯",
        "link": "https://trends.google.com/trends/trendingsearches/daily?geo=HK#%E6%B3%A2%E5%9C%96%20%E5%B0%8D%E6%9B%BC%E8%81%AF",
        "pubdate": "Fri, 04 Oct 2024 03:00:00 +0800"
    },
    {
        "title": "День учителя",
        "link": "https://trends.google.com/trends/trendingsearches/daily?geo=RU#%D0%94%D0%B5%D0%BD%D1%8C%20%D1%83%D1%87%D0%B8%D1%82%D0%B5%D0%BB%D1%8F",
        "pubdate": "Fri, 04 Oct 2024 07:00:00 +0300"
    },
    {
        "title": "Eminem",
        "link": "https://trends.google.com/trends/trendingsearches/daily?geo=GR#Eminem",
        "pubdate": "Fri, 04 Oct 2024 00:00:00 +0300"
    },
    {
        "title": "Fideicomiso River",
        "link": "https://trends.google.com/trends/trendingsearches/daily?geo=AR#Fideicomiso%20River",
        "pubdate": "Fri, 04 Oct 2024 02:00:00 -0300"
    },
    {
        "title": "Dia del odontologo",
        "link": "https://trends.google.com/trends/trendingsearches/daily?geo=PE#Dia%20del%20odontologo",
        "pubdate": "Fri, 04 Oct 2024 00:00:00 -0500"
    },
    {
        "title": "Galatasaray",
        "link": "https://trends.google.com/trends/trendingsearches/daily?geo=RO#Galatasaray",
        "pubdate": "Fri, 04 Oct 2024 08:00:00 +0300"
    },
    {
        "title": "هاشم صفي الدين حزب الله",
        "link": "https://trends.google.com/trends/trendingsearches/daily?geo=SA#%D9%87%D8%A7%D8%B4%D9%85%20%D8%B5%D9%81%D9%8A%20%D8%A7%D9%84%D8%AF%D9%8A%D9%86%20%D8%AD%D8%B2%D8%A8%20%D8%A7%D9%84%D9%84%D9%87",
        "pubdate": "Fri, 04 Oct 2024 01:00:00 +0300"
    },
    {
        "title": "هاشم صفي الدين",
        "link": "https://trends.google.com/trends/trendingsearches/daily?geo=EG#%D9%87%D8%A7%D8%B4%D9%85%20%D8%B5%D9%81%D9%8A%20%D8%A7%D9%84%D8%AF%D9%8A%D9%86",
        "pubdate": "Fri, 04 Oct 2024 01:00:00 +0300"
    },
    {
        "title": "Chelsea vs Gent",
        "link": "https://trends.google.com/trends/trendingsearches/daily?geo=MY#Chelsea%20vs%20Gent",
        "pubdate": "Fri, 04 Oct 2024 03:00:00 +0800"
    },
    {
        "title": "Porto đấu với Man Utd",
        "link": "https://trends.google.com/trends/trendingsearches/daily?geo=VN#Porto%20%C4%91%E1%BA%A5u%20v%E1%BB%9Bi%20Man%20Utd",
        "pubdate": "Fri, 04 Oct 2024 02:00:00 +0700"
    },
    {
        "title": "SK Slavia Praha",
        "link": "https://trends.google.com/trends/trendingsearches/daily?geo=CZ#SK%20Slavia%20Praha",
        "pubdate": "Fri, 04 Oct 2024 00:00:00 +0200"
    },
    {
        "title": "Dan Da Dan",
        "link": "https://trends.google.com/trends/trendingsearches/daily?geo=BR#Dan%20Da%20Dan",
        "pubdate": "Fri, 04 Oct 2024 00:00:00 -0500"
    },
    {
        "title": "Garth Brooks",
        "link": "https://trends.google.com/trends/trendingsearches/daily?geo=IE#Garth%20Brooks",
        "pubdate": "Fri, 04 Oct 2024 04:00:00 +0100"
    },
    {
        "title": "แมนยู",
        "link": "https://trends.google.com/trends/trendingsearches/daily?geo=TH#%E0%B9%81%E0%B8%A1%E0%B8%99%E0%B8%A2%E0%B8%B9",
        "pubdate": "Fri, 04 Oct 2024 04:00:00 +0700"
    }
]