[
    {
        "title": "Xavier Niel",
        "link": "https://trends.google.com/trends/trendingsearches/daily?geo=FR#Xavier%20Niel",
        "pubdate": "Tue, 01 Oct 2024 10:00:00 +0200"
    },
    {
        "title": "電影",
        "link": "https://trends.google.com/trends/trendingsearches/daily?geo=HK#%E9%9B%BB%E5%BD%B1",
        "pubdate": "Tue, 01 Oct 2024 16:00:00 +0800"
    },
    {
        "title": "Verizon",
        "link": "https://trends.google.com/trends/trendingsearches/daily?geo=US#Verizon",
        "pubdate": "Mon, 30 Sep 2024 09:00:00 -0700"
    },
    {
        "title": "Govinda",
        "link": "https://trends.google.com/trends/trendingsearches/daily?geo=IN#Govinda",
        "pubdate": "Tue, 01 Oct 2024 10:30:00 +0530"
    },
    {
        "title": "Champions League",
        "link": "https://trends.google.com/trends/trendingsearches/daily?geo=GB#Champions%20League",
        "pubdate": "Tue, 01 Oct 2024 01:00:00 +0100"
    },
    {
        "title": "Вячеслав Добрынин",
        "link": "https://trends.google.com/trends/trendingsearches/daily?geo=RU#%D0%92%D1%8F%D1%87%D0%B5%D1%81%D0%BB%D0%B0%D0%B2%20%D0%94%D0%BE%D0%B1%D1%80%D1%8B%D0%BD%D0%B8%D0%BD",
        "pubdate": "Tue, 01 Oct 2024 13:00:00 +0300"
    },
    {
        "title": "台風気象情報、台風第17号",
        "link": "https://trends.google.com/trends/trendingsearches/daily?geo=JP#%E5%8F%B0%E9%A2%A8%E6%B0%97%E8%B1%A1%E6%83%85%E5%A0%B1%E3%80%81%E5%8F%B0%E9%A2%A8%E7%AC%AC17%E5%8F%B7",
        "pubdate": "Tue, 01 Oct 2024 11:00:00 +0900"
    },
    {
        "title": "Kris Kristofferson",
        "link": "https://trends.google.com/trends/trendingsearches/daily?geo=DE#Kris%20Kristofferson",
        "pubdate": "Mon, 30 Sep 2024 04:00:00 +0200"
    },
    {
        "title": "Daniel Chanoch",
        "link": "https://trends.google.com/trends/trendingsearches/daily?geo=AT#Daniel%20Chanoch",
        "pubdate": "Tue, 01 Oct 2024 07:00:00 +0200"
    },
    {
        "title": "دوري ابطال اوروبا",
        "link": "https://trends.google.com/trends/trendingsearches/daily?geo=EG#%D8%AF%D9%88%D8%B1%D9%8A%20%D8%A7%D8%A8%D8%B7%D8%A7%D9%84%20%D8%A7%D9%88%D8%B1%D9%88%D8%A8%D8%A7",
        "pubdate": "Tue, 01 Oct 2024 13:00:00 +0300"
    },
    {
        "title": "PlayStation Network",
        "link": "https://trends.google.com/trends/trendingsearches/daily?geo=CL#PlayStation%20Network",
        "pubdate": "Tue, 01 Oct 2024 00:00:00 -0300"
    },
    {
        "title": "صفاء احمد",
        "link": "https://trends.google.com/trends/trendingsearches/daily?geo=SA#%D8%B5%D9%81%D8%A7%D8%A1%20%D8%A7%D8%AD%D9%85%D8%AF",
        "pubdate": "Tue, 01 Oct 2024 05:00:00 +0300"
    },
    {
        "title": "Que se celebra El 1 de octubre",
        "link": "https://trends.google.com/trends/trendingsearches/daily?geo=CO#Que%20se%20celebra%20El%201%20de%20octubre",
        "pubdate": "Tue, 01 Oct 2024 00:00:00 -0500"
    },
    {
        "title": "Mutombo",
        "link": "https://trends.google.com/trends/trendingsearches/daily?geo=TW#Mutombo",
        "pubdate": "Tue, 01 Oct 2024 00:00:00 +0800"
    },
    {
        "title": "포항 대 상하이 하이강",
        "link": "https://trends.google.com/trends/trendingsearches/daily?geo=KR#%ED%8F%AC%ED%95%AD%20%EB%8C%80%20%EC%83%81%ED%95%98%EC%9D%B4%20%ED%95%98%EC%9D%B4%EA%B0%95",
        "pubdate": "Tue, 01 Oct 2024 19:00:00 +0900"
    },
    {
        "title": "Mark Rutte",
        "link": "https://trends.google.com/trends/trendingsearches/daily?geo=NO#Mark%20Rutte",
        "pubdate": "Tue, 01 Oct 2024 10:00:00 +0200"
    },
    {
        "title": "Puff daddy",
        "link": "https://trends.google.com/trends/trendingsearches/daily?geo=HU#Puff%20daddy",
        "pubdate": "Tue, 01 Oct 2024 11:00:00 +0200"
    },
    {
        "title": "MyDigital ID",
        "link": "https://trends.google.com/trends/trendingsearches/daily?geo=MY#MyDigital%20ID",
        "pubdate": "Tue, 01 Oct 2024 09:00:00 +0800"
    },
    {
        "title": "1 de octubre",
        "link": "https://trends.google.com/trends/trendingsearches/daily?geo=PE#1%20de%20octubre",
        "pubdate": "Tue, 01 Oct 2024 07:00:00 -0500"
    },
    {
        "title": "Gaston Edul",
        "link": "https://trends.google.com/trends/trendingsearches/daily?geo=AR#Gaston%20Edul",
        "pubdate": "Tue, 01 Oct 2024 00:00:00 -0300"
    }
]