[
    {
        "title": "Bruno Retailleau ministre",
        "link": "https://trends.google.com/trends/trendingsearches/daily?geo=FR#Bruno%20Retailleau%20ministre",
        "pubdate": "Wed, 02 Oct 2024 00:00:00 +0200"
    },
    {
        "title": "Champions-League",
        "link": "https://trends.google.com/trends/trendingsearches/daily?geo=DE#Champions-League",
        "pubdate": "Tue, 01 Oct 2024 09:00:00 +0200"
    },
    {
        "title": "Israel",
        "link": "https://trends.google.com/trends/trendingsearches/daily?geo=IN#Israel",
        "pubdate": "Wed, 02 Oct 2024 01:30:00 +0530"
    },
    {
        "title": "Утильсбор",
        "link": "https://trends.google.com/trends/trendingsearches/daily?geo=RU#%D0%A3%D1%82%D0%B8%D0%BB%D1%8C%D1%81%D0%B1%D0%BE%D1%80",
        "pubdate": "Wed, 02 Oct 2024 02:00:00 +0300"
    },
    {
        "title": "イスラエル",
        "link": "https://trends.google.com/trends/trendingsearches/daily?geo=JP#%E3%82%A4%E3%82%B9%E3%83%A9%E3%82%A8%E3%83%AB",
        "pubdate": "Wed, 02 Oct 2024 03:00:00 +0900"
    },
    {
        "title": "John Amos",
        "link": "https://trends.google.com/trends/trendingsearches/daily?geo=US#John%20Amos",
        "pubdate": "Tue, 01 Oct 2024 12:00:00 -0700"
    },
    {
        "title": "CNN",
        "link": "https://trends.google.com/trends/trendingsearches/daily?geo=GB#CNN",
        "pubdate": "Wed, 02 Oct 2024 07:00:00 +0100"
    },
    {
        "title": "伊朗",
        "link": "https://trends.google.com/trends/trendingsearches/daily?geo=HK#%E4%BC%8A%E6%9C%97",
        "pubdate": "Wed, 02 Oct 2024 00:00:00 +0800"
    },
    {
        "title": "Barcelona",
        "link": "https://trends.google.com/trends/trendingsearches/daily?geo=PE#Barcelona",
        "pubdate": "Tue, 01 Oct 2024 11:00:00 -0500"
    },
    {
        "title": "Perimenopause",
        "link": "https://trends.google.com/trends/trendingsearches/daily?geo=NO#Perimenopause",
        "pubdate": "Wed, 02 Oct 2024 08:00:00 +0200"
    },
    {
        "title": "News",
        "link": "https://trends.google.com/trends/trendingsearches/daily?geo=DK#News",
        "pubdate": "Wed, 02 Oct 2024 03:00:00 +0200"
    },
    {
        "title": "JD Vance",
        "link": "https://trends.google.com/trends/trendingsearches/daily?geo=SE#JD%20Vance",
        "pubdate": "Wed, 02 Oct 2024 08:00:00 +0200"
    },
    {
        "title": "Iran",
        "link": "https://trends.google.com/trends/trendingsearches/daily?geo=NZ#Iran",
        "pubdate": "Wed, 02 Oct 2024 08:00:00 +1300"
    },
    {
        "title": "Ryujinx",
        "link": "https://trends.google.com/trends/trendingsearches/daily?geo=BR#Ryujinx",
        "pubdate": "Wed, 02 Oct 2024 00:00:00 -0500"
    },
    {
        "title": "Michael Schumacher",
        "link": "https://trends.google.com/trends/trendingsearches/daily?geo=AT#Michael%20Schumacher",
        "pubdate": "Wed, 02 Oct 2024 08:00:00 +0200"
    },
    {
        "title": "Arsenal vs PSG",
        "link": "https://trends.google.com/trends/trendingsearches/daily?geo=ZA#Arsenal%20vs%20PSG",
        "pubdate": "Tue, 01 Oct 2024 10:00:00 +0200"
    },
    {
        "title": "Paulina Matysiak",
        "link": "https://trends.google.com/trends/trendingsearches/daily?geo=PL#Paulina%20Matysiak",
        "pubdate": "Wed, 02 Oct 2024 00:00:00 +0200"
    },
    {
        "title": "Acmilan",
        "link": "https://trends.google.com/trends/trendingsearches/daily?geo=IT#Acmilan",
        "pubdate": "Wed, 02 Oct 2024 00:00:00 +0200"
    },
    {
        "title": "電影",
        "link": "https://trends.google.com/trends/trendingsearches/daily?geo=TW#%E9%9B%BB%E5%BD%B1",
        "pubdate": "Wed, 02 Oct 2024 14:00:00 +0800"
    },
    {
        "title": "Slovan Bratislava vs Man City",
        "link": "https://trends.google.com/trends/trendingsearches/daily?geo=SG#Slovan%20Bratislava%20vs%20Man%20City",
        "pubdate": "Wed, 02 Oct 2024 04:00:00 +0800"
    }
]