[
    {
        "title": "Real Madrid – Manchester City",
        "link": "https://trends.google.com/trends/trendingsearches/daily?geo=FR#Real%20Madrid%20%E2%80%93%20Manchester%20City",
        "pubdate": "Wed, 19 Feb 2025 00:00:00 +0100"
    },
    {
        "title": "AC Milan",
        "link": "https://trends.google.com/trends/trendingsearches/daily?geo=US#AC%20Milan",
        "pubdate": "Tue, 18 Feb 2025 11:00:00 -0800"
    },
    {
        "title": "Бенфика – Монако",
        "link": "https://trends.google.com/trends/trendingsearches/daily?geo=RU#%D0%91%D0%B5%D0%BD%D1%84%D0%B8%D0%BA%D0%B0%20%E2%80%93%20%D0%9C%D0%BE%D0%BD%D0%B0%D0%BA%D0%BE",
        "pubdate": "Wed, 19 Feb 2025 00:00:00 +0300"
    },
    {
        "title": "FC Bayern",
        "link": "https://trends.google.com/trends/trendingsearches/daily?geo=DE#FC%20Bayern",
        "pubdate": "Tue, 18 Feb 2025 21:00:00 +0100"
    },
    {
        "title": "MOBO Awards 2025",
        "link": "https://trends.google.com/trends/trendingsearches/daily?geo=GB#MOBO%20Awards%202025",
        "pubdate": "Wed, 19 Feb 2025 01:00:00 +0000"
    },
    {
        "title": "伊勢湾岸道 事故",
        "link": "https://trends.google.com/trends/trendingsearches/daily?geo=JP#%E4%BC%8A%E5%8B%A2%E6%B9%BE%E5%B2%B8%E9%81%93%20%E4%BA%8B%E6%95%85",
        "pubdate": "Wed, 19 Feb 2025 02:00:00 +0900"
    },
    {
        "title": "Chhatrapati Shivaji Maharaj Jayanti",
        "link": "https://trends.google.com/trends/trendingsearches/daily?geo=IN#Chhatrapati%20Shivaji%20Maharaj%20Jayanti",
        "pubdate": "Wed, 19 Feb 2025 00:30:00 +0530"
    },
    {
        "title": "謝霆鋒演唱會",
        "link": "https://trends.google.com/trends/trendingsearches/daily?geo=HK#%E8%AC%9D%E9%9C%86%E9%8B%92%E6%BC%94%E5%94%B1%E6%9C%83",
        "pubdate": "Wed, 19 Feb 2025 01:00:00 +0800"
    },
    {
        "title": "Milan  Feyenoord",
        "link": "https://trends.google.com/trends/trendingsearches/daily?geo=AR#Milan%20%20Feyenoord",
        "pubdate": "Tue, 18 Feb 2025 15:00:00 -0300"
    },
    {
        "title": "Ella Halvarsson",
        "link": "https://trends.google.com/trends/trendingsearches/daily?geo=SE#Ella%20Halvarsson",
        "pubdate": "Tue, 18 Feb 2025 17:00:00 +0100"
    },
    {
        "title": "Milan vs Feyenoord",
        "link": "https://trends.google.com/trends/trendingsearches/daily?geo=ID#Milan%20vs%20Feyenoord",
        "pubdate": "Tue, 18 Feb 2025 23:00:00 +0700"
    },
    {
        "title": "Atalanta  Club Brugge",
        "link": "https://trends.google.com/trends/trendingsearches/daily?geo=TR#Atalanta%20%20Club%20Brugge",
        "pubdate": "Wed, 19 Feb 2025 00:00:00 +0300"
    },
    {
        "title": "Evaristo",
        "link": "https://trends.google.com/trends/trendingsearches/daily?geo=ES#Evaristo",
        "pubdate": "Wed, 19 Feb 2025 00:00:00 +0100"
    },
    {
        "title": "Μπαγερν",
        "link": "https://trends.google.com/trends/trendingsearches/daily?geo=GR#%CE%9C%CF%80%CE%B1%CE%B3%CE%B5%CF%81%CE%BD",
        "pubdate": "Wed, 19 Feb 2025 00:00:00 +0200"
    },
    {
        "title": "Bayern vs Celtic",
        "link": "https://trends.google.com/trends/trendingsearches/daily?geo=KE#Bayern%20vs%20Celtic",
        "pubdate": "Tue, 18 Feb 2025 20:00:00 +0300"
    },
    {
        "title": "Бенфіка – Монако",
        "link": "https://trends.google.com/trends/trendingsearches/daily?geo=UA#%D0%91%D0%B5%D0%BD%D1%84%D1%96%D0%BA%D0%B0%20%E2%80%93%20%D0%9C%D0%BE%D0%BD%D0%B0%D0%BA%D0%BE",
        "pubdate": "Tue, 18 Feb 2025 23:00:00 +0200"
    },
    {
        "title": "Bayern  Celtic FC",
        "link": "https://trends.google.com/trends/trendingsearches/daily?geo=MX#Bayern%20%20Celtic%20FC",
        "pubdate": "Tue, 18 Feb 2025 12:00:00 -0600"
    },
    {
        "title": "Novak Djokovic",
        "link": "https://trends.google.com/trends/trendingsearches/daily?geo=AU#Novak%20Djokovic",
        "pubdate": "Wed, 19 Feb 2025 07:00:00 +1100"
    },
    {
        "title": "Grok 3",
        "link": "https://trends.google.com/trends/trendingsearches/daily?geo=NZ#Grok%203",
        "pubdate": "Wed, 19 Feb 2025 00:00:00 +1300"
    },
    {
        "title": "Atalanta",
        "link": "https://trends.google.com/trends/trendingsearches/daily?geo=RO#Atalanta",
        "pubdate": "Wed, 19 Feb 2025 00:00:00 +0200"
    }
]