[
    {
        "title": "Temblor hoy",
        "link": "https://trends.google.com/trends/trendingsearches/daily?geo=PE#Temblor%20hoy",
        "pubdate": "Mon, 30 Sep 2024 07:00:00 -0500"
    },
    {
        "title": "Al-nassr  al-rayyan",
        "link": "https://trends.google.com/trends/trendingsearches/daily?geo=PE#Al-nassr%20%20al-rayyan",
        "pubdate": "Mon, 30 Sep 2024 13:00:00 -0500"
    },
    {
        "title": "Villarreal  UD Las Palmas",
        "link": "https://trends.google.com/trends/trendingsearches/daily?geo=PE#Villarreal%20%20UD%20Las%20Palmas",
        "pubdate": "Mon, 30 Sep 2024 14:00:00 -0500"
    },
    {
        "title": "Hot Wheels",
        "link": "https://trends.google.com/trends/trendingsearches/daily?geo=PE#Hot%20Wheels",
        "pubdate": "Mon, 30 Sep 2024 13:00:00 -0500"
    },
    {
        "title": "Parma-Cagliari",
        "link": "https://trends.google.com/trends/trendingsearches/daily?geo=PE#Parma-Cagliari",
        "pubdate": "Mon, 30 Sep 2024 14:00:00 -0500"
    },
    {
        "title": "30 de septiembre que se celebra",
        "link": "https://trends.google.com/trends/trendingsearches/daily?geo=PE#30%20de%20septiembre%20que%20se%20celebra",
        "pubdate": "Mon, 30 Sep 2024 00:00:00 -0500"
    },
    {
        "title": "Peru vs",
        "link": "https://trends.google.com/trends/trendingsearches/daily?geo=PE#Peru%20vs",
        "pubdate": "Mon, 30 Sep 2024 09:00:00 -0500"
    },
    {
        "title": "Temblor",
        "link": "https://trends.google.com/trends/trendingsearches/daily?geo=PE#Temblor",
        "pubdate": "Mon, 30 Sep 2024 15:00:00 -0500"
    },
    {
        "title": "Feriados Octubre 2024",
        "link": "https://trends.google.com/trends/trendingsearches/daily?geo=PE#Feriados%20Octubre%202024",
        "pubdate": "Mon, 30 Sep 2024 09:00:00 -0500"
    },
    {
        "title": "Bournemouth  Southampton",
        "link": "https://trends.google.com/trends/trendingsearches/daily?geo=PE#Bournemouth%20%20Southampton",
        "pubdate": "Mon, 30 Sep 2024 15:00:00 -0500"
    },
    {
        "title": "Atletico Grau",
        "link": "https://trends.google.com/trends/trendingsearches/daily?geo=PE#Atletico%20Grau",
        "pubdate": "Mon, 30 Sep 2024 14:00:00 -0500"
    },
    {
        "title": "Calcaterra",
        "link": "https://trends.google.com/trends/trendingsearches/daily?geo=PE#Calcaterra",
        "pubdate": "Mon, 30 Sep 2024 12:00:00 -0500"
    },
    {
        "title": "Feriados octubre",
        "link": "https://trends.google.com/trends/trendingsearches/daily?geo=PE#Feriados%20octubre",
        "pubdate": "Mon, 30 Sep 2024 11:00:00 -0500"
    },
    {
        "title": "Griezmann",
        "link": "https://trends.google.com/trends/trendingsearches/daily?geo=PE#Griezmann",
        "pubdate": "Mon, 30 Sep 2024 12:00:00 -0500"
    },
    {
        "title": "Decreto Legislativo 1669",
        "link": "https://trends.google.com/trends/trendingsearches/daily?geo=PE#Decreto%20Legislativo%201669",
        "pubdate": "Mon, 30 Sep 2024 12:00:00 -0500"
    },
    {
        "title": "Beyonce",
        "link": "https://trends.google.com/trends/trendingsearches/daily?geo=PE#Beyonce",
        "pubdate": "Mon, 30 Sep 2024 02:00:00 -0500"
    },
    {
        "title": "Besiktas",
        "link": "https://trends.google.com/trends/trendingsearches/daily?geo=PE#Besiktas",
        "pubdate": "Mon, 30 Sep 2024 15:00:00 -0500"
    },
    {
        "title": "Señor de los Milagros",
        "link": "https://trends.google.com/trends/trendingsearches/daily?geo=PE#Se%C3%B1or%20de%20los%20Milagros",
        "pubdate": "Mon, 30 Sep 2024 13:00:00 -0500"
    },
    {
        "title": "Sao Paulo vs Corinthians",
        "link": "https://trends.google.com/trends/trendingsearches/daily?geo=PE#Sao%20Paulo%20vs%20Corinthians",
        "pubdate": "Mon, 30 Sep 2024 02:00:00 -0500"
    },
    {
        "title": "Comerciantes Unidos  Universitario",
        "link": "https://trends.google.com/trends/trendingsearches/daily?geo=PE#Comerciantes%20Unidos%20%20Universitario",
        "pubdate": "Sun, 29 Sep 2024 01:00:00 -0500"
    }
]