[
    {
        "title": "Bucaramanga  Millonarios",
        "link": "https://trends.google.com/trends/trendingsearches/daily?geo=PE#Bucaramanga%20%20Millonarios",
        "pubdate": "Wed, 09 Oct 2024 00:00:00 -0500"
    },
    {
        "title": "Shakira en peru",
        "link": "https://trends.google.com/trends/trendingsearches/daily?geo=PE#Shakira%20en%20peru",
        "pubdate": "Tue, 08 Oct 2024 12:00:00 -0500"
    },
    {
        "title": "Peru vs Chile Sub 15",
        "link": "https://trends.google.com/trends/trendingsearches/daily?geo=PE#Peru%20vs%20Chile%20Sub%2015",
        "pubdate": "Tue, 08 Oct 2024 19:00:00 -0500"
    },
    {
        "title": "Miniso",
        "link": "https://trends.google.com/trends/trendingsearches/daily?geo=PE#Miniso",
        "pubdate": "Tue, 08 Oct 2024 23:00:00 -0500"
    },
    {
        "title": "Andres Iniesta",
        "link": "https://trends.google.com/trends/trendingsearches/daily?geo=PE#Andres%20Iniesta",
        "pubdate": "Tue, 08 Oct 2024 16:00:00 -0500"
    },
    {
        "title": "Michael Schumacher",
        "link": "https://trends.google.com/trends/trendingsearches/daily?geo=PE#Michael%20Schumacher",
        "pubdate": "Tue, 08 Oct 2024 22:00:00 -0500"
    },
    {
        "title": "Evo Morales",
        "link": "https://trends.google.com/trends/trendingsearches/daily?geo=PE#Evo%20Morales",
        "pubdate": "Tue, 08 Oct 2024 18:00:00 -0500"
    },
    {
        "title": "Combate de Angamos",
        "link": "https://trends.google.com/trends/trendingsearches/daily?geo=PE#Combate%20de%20Angamos",
        "pubdate": "Mon, 07 Oct 2024 01:00:00 -0500"
    },
    {
        "title": "Huracan Milton hoy",
        "link": "https://trends.google.com/trends/trendingsearches/daily?geo=PE#Huracan%20Milton%20hoy",
        "pubdate": "Mon, 07 Oct 2024 17:00:00 -0500"
    },
    {
        "title": "8 de octubre que se celebra",
        "link": "https://trends.google.com/trends/trendingsearches/daily?geo=PE#8%20de%20octubre%20que%20se%20celebra",
        "pubdate": "Mon, 07 Oct 2024 08:00:00 -0500"
    },
    {
        "title": "Dragon Ball: Sparking! Zero",
        "link": "https://trends.google.com/trends/trendingsearches/daily?geo=PE#Dragon%20Ball:%20Sparking!%20Zero",
        "pubdate": "Mon, 07 Oct 2024 15:00:00 -0500"
    },
    {
        "title": "Sammy Basso progeria",
        "link": "https://trends.google.com/trends/trendingsearches/daily?geo=PE#Sammy%20Basso%20progeria",
        "pubdate": "Mon, 07 Oct 2024 23:00:00 -0500"
    },
    {
        "title": "Copa Libertadores femenina",
        "link": "https://trends.google.com/trends/trendingsearches/daily?geo=PE#Copa%20Libertadores%20femenina",
        "pubdate": "Mon, 07 Oct 2024 16:00:00 -0500"
    },
    {
        "title": "Deportivo Cali  Alianza Lima",
        "link": "https://trends.google.com/trends/trendingsearches/daily?geo=PE#Deportivo%20Cali%20%20Alianza%20Lima",
        "pubdate": "Mon, 07 Oct 2024 16:00:00 -0500"
    },
    {
        "title": "Gero Arias",
        "link": "https://trends.google.com/trends/trendingsearches/daily?geo=PE#Gero%20Arias",
        "pubdate": "Mon, 07 Oct 2024 21:00:00 -0500"
    },
    {
        "title": "Defensa y Justicia  Rosario Central",
        "link": "https://trends.google.com/trends/trendingsearches/daily?geo=PE#Defensa%20y%20Justicia%20%20Rosario%20Central",
        "pubdate": "Mon, 07 Oct 2024 19:00:00 -0500"
    },
    {
        "title": "Balon de Oro 2024",
        "link": "https://trends.google.com/trends/trendingsearches/daily?geo=PE#Balon%20de%20Oro%202024",
        "pubdate": "Mon, 07 Oct 2024 20:00:00 -0500"
    },
    {
        "title": "Banco de la Nación",
        "link": "https://trends.google.com/trends/trendingsearches/daily?geo=PE#Banco%20de%20la%20Naci%C3%B3n",
        "pubdate": "Mon, 07 Oct 2024 13:00:00 -0500"
    },
    {
        "title": "Primera División",
        "link": "https://trends.google.com/trends/trendingsearches/daily?geo=PE#Primera%20Divisi%C3%B3n",
        "pubdate": "Mon, 07 Oct 2024 10:00:00 -0500"
    },
    {
        "title": "Barracas Central",
        "link": "https://trends.google.com/trends/trendingsearches/daily?geo=PE#Barracas%20Central",
        "pubdate": "Mon, 07 Oct 2024 16:00:00 -0500"
    }
]