[
    {
        "title": "Garcia Pelayo",
        "link": "https://trends.google.com/trends/trendingsearches/daily?geo=ES#Garcia%20Pelayo",
        "pubdate": "Tue, 24 Dec 2024 00:00:00 +0100"
    },
    {
        "title": "Nochebuena",
        "link": "https://trends.google.com/trends/trendingsearches/daily?geo=ES#Nochebuena",
        "pubdate": "Tue, 24 Dec 2024 01:00:00 +0100"
    },
    {
        "title": "Feliz Navidad",
        "link": "https://trends.google.com/trends/trendingsearches/daily?geo=ES#Feliz%20Navidad",
        "pubdate": "Mon, 23 Dec 2024 20:00:00 +0100"
    },
    {
        "title": "Isabel Preysler",
        "link": "https://trends.google.com/trends/trendingsearches/daily?geo=ES#Isabel%20Preysler",
        "pubdate": "Mon, 23 Dec 2024 23:00:00 +0100"
    },
    {
        "title": "Jesus-navas",
        "link": "https://trends.google.com/trends/trendingsearches/daily?geo=ES#Jesus-navas",
        "pubdate": "Mon, 23 Dec 2024 15:00:00 +0100"
    },
    {
        "title": "Madrid",
        "link": "https://trends.google.com/trends/trendingsearches/daily?geo=ES#Madrid",
        "pubdate": "Mon, 23 Dec 2024 01:00:00 +0100"
    },
    {
        "title": "Los Reyes Catarroja",
        "link": "https://trends.google.com/trends/trendingsearches/daily?geo=ES#Los%20Reyes%20Catarroja",
        "pubdate": "Mon, 23 Dec 2024 00:00:00 +0100"
    },
    {
        "title": "Grison",
        "link": "https://trends.google.com/trends/trendingsearches/daily?geo=ES#Grison",
        "pubdate": "Mon, 23 Dec 2024 15:00:00 +0100"
    },
    {
        "title": "Antena 3",
        "link": "https://trends.google.com/trends/trendingsearches/daily?geo=ES#Antena%203",
        "pubdate": "Mon, 23 Dec 2024 00:00:00 +0100"
    },
    {
        "title": "Dos presos se fugan de Picassent",
        "link": "https://trends.google.com/trends/trendingsearches/daily?geo=ES#Dos%20presos%20se%20fugan%20de%20Picassent",
        "pubdate": "Mon, 23 Dec 2024 08:00:00 +0100"
    },
    {
        "title": "Inter  Como",
        "link": "https://trends.google.com/trends/trendingsearches/daily?geo=ES#Inter%20%20Como",
        "pubdate": "Mon, 23 Dec 2024 22:00:00 +0100"
    },
    {
        "title": "Rayo Vallecano",
        "link": "https://trends.google.com/trends/trendingsearches/daily?geo=ES#Rayo%20Vallecano",
        "pubdate": "Mon, 23 Dec 2024 11:00:00 +0100"
    },
    {
        "title": "Muface funcionarios",
        "link": "https://trends.google.com/trends/trendingsearches/daily?geo=ES#Muface%20funcionarios",
        "pubdate": "Mon, 23 Dec 2024 17:00:00 +0100"
    },
    {
        "title": "Atlético Nacional  Tolima",
        "link": "https://trends.google.com/trends/trendingsearches/daily?geo=ES#Atl%C3%A9tico%20Nacional%20%20Tolima",
        "pubdate": "Mon, 23 Dec 2024 01:00:00 +0100"
    },
    {
        "title": "Felices Fiestas",
        "link": "https://trends.google.com/trends/trendingsearches/daily?geo=ES#Felices%20Fiestas",
        "pubdate": "Mon, 23 Dec 2024 15:00:00 +0100"
    },
    {
        "title": "Cristina Pedroche",
        "link": "https://trends.google.com/trends/trendingsearches/daily?geo=ES#Cristina%20Pedroche",
        "pubdate": "Mon, 23 Dec 2024 15:00:00 +0100"
    },
    {
        "title": "Loteria de Navidad 2024 comprobar numero",
        "link": "https://trends.google.com/trends/trendingsearches/daily?geo=ES#Loteria%20de%20Navidad%202024%20comprobar%20numero",
        "pubdate": "Mon, 23 Dec 2024 09:00:00 +0100"
    },
    {
        "title": "Fiorentina - Udinese",
        "link": "https://trends.google.com/trends/trendingsearches/daily?geo=ES#Fiorentina%20-%20Udinese",
        "pubdate": "Mon, 23 Dec 2024 21:00:00 +0100"
    },
    {
        "title": "GH duo",
        "link": "https://trends.google.com/trends/trendingsearches/daily?geo=ES#GH%20duo",
        "pubdate": "Mon, 23 Dec 2024 10:00:00 +0100"
    },
    {
        "title": "Julio Iglesias",
        "link": "https://trends.google.com/trends/trendingsearches/daily?geo=ES#Julio%20Iglesias",
        "pubdate": "Mon, 23 Dec 2024 23:00:00 +0100"
    }
]