[
    {
        "title": "Inter Miami - New England",
        "link": "https://trends.google.com/trends/trendingsearches/daily?geo=ES#Inter%20Miami%20-%20New%20England",
        "pubdate": "Sun, 20 Oct 2024 01:00:00 +0200"
    },
    {
        "title": "Pez aguja",
        "link": "https://trends.google.com/trends/trendingsearches/daily?geo=ES#Pez%20aguja",
        "pubdate": "Sun, 20 Oct 2024 00:00:00 +0200"
    },
    {
        "title": "Julio Iglesias",
        "link": "https://trends.google.com/trends/trendingsearches/daily?geo=ES#Julio%20Iglesias",
        "pubdate": "Sun, 20 Oct 2024 01:00:00 +0200"
    },
    {
        "title": "Bilbao Night Marathon",
        "link": "https://trends.google.com/trends/trendingsearches/daily?geo=ES#Bilbao%20Night%20Marathon",
        "pubdate": "Sun, 20 Oct 2024 00:00:00 +0200"
    },
    {
        "title": "Tom Hanks",
        "link": "https://trends.google.com/trends/trendingsearches/daily?geo=ES#Tom%20Hanks",
        "pubdate": "Sun, 20 Oct 2024 00:00:00 +0200"
    },
    {
        "title": "PSG",
        "link": "https://trends.google.com/trends/trendingsearches/daily?geo=ES#PSG",
        "pubdate": "Sun, 20 Oct 2024 00:00:00 +0200"
    },
    {
        "title": "MotoGP hoy",
        "link": "https://trends.google.com/trends/trendingsearches/daily?geo=ES#MotoGP%20hoy",
        "pubdate": "Sun, 20 Oct 2024 10:00:00 +0200"
    },
    {
        "title": "Barça hoy",
        "link": "https://trends.google.com/trends/trendingsearches/daily?geo=ES#Bar%C3%A7a%20hoy",
        "pubdate": "Sun, 20 Oct 2024 10:00:00 +0200"
    },
    {
        "title": "Celta de Vigo - Real Madrid",
        "link": "https://trends.google.com/trends/trendingsearches/daily?geo=ES#Celta%20de%20Vigo%20-%20Real%20Madrid",
        "pubdate": "Sat, 19 Oct 2024 16:00:00 +0200"
    },
    {
        "title": "Athletic  RCD Espanyol",
        "link": "https://trends.google.com/trends/trendingsearches/daily?geo=ES#Athletic%20%20RCD%20Espanyol",
        "pubdate": "Sat, 19 Oct 2024 14:00:00 +0200"
    },
    {
        "title": "Osasuna - Betis",
        "link": "https://trends.google.com/trends/trendingsearches/daily?geo=ES#Osasuna%20-%20Betis",
        "pubdate": "Sat, 19 Oct 2024 16:00:00 +0200"
    },
    {
        "title": "Girona - Real Sociedad",
        "link": "https://trends.google.com/trends/trendingsearches/daily?geo=ES#Girona%20-%20Real%20Sociedad",
        "pubdate": "Sat, 19 Oct 2024 18:00:00 +0200"
    },
    {
        "title": "Nadal Djokovic",
        "link": "https://trends.google.com/trends/trendingsearches/daily?geo=ES#Nadal%20Djokovic",
        "pubdate": "Sat, 19 Oct 2024 12:00:00 +0200"
    },
    {
        "title": "F1",
        "link": "https://trends.google.com/trends/trendingsearches/daily?geo=ES#F1",
        "pubdate": "Sat, 19 Oct 2024 00:00:00 +0200"
    },
    {
        "title": "Premier League",
        "link": "https://trends.google.com/trends/trendingsearches/daily?geo=ES#Premier%20League",
        "pubdate": "Sat, 19 Oct 2024 01:00:00 +0200"
    },
    {
        "title": "Granada - Tenerife",
        "link": "https://trends.google.com/trends/trendingsearches/daily?geo=ES#Granada%20-%20Tenerife",
        "pubdate": "Sat, 19 Oct 2024 19:00:00 +0200"
    },
    {
        "title": "Málaga  Real Oviedo",
        "link": "https://trends.google.com/trends/trendingsearches/daily?geo=ES#M%C3%A1laga%20%20Real%20Oviedo",
        "pubdate": "Sat, 19 Oct 2024 16:00:00 +0200"
    },
    {
        "title": "DAZN",
        "link": "https://trends.google.com/trends/trendingsearches/daily?geo=ES#DAZN",
        "pubdate": "Sat, 19 Oct 2024 20:00:00 +0200"
    },
    {
        "title": "Manchester United  Brentford",
        "link": "https://trends.google.com/trends/trendingsearches/daily?geo=ES#Manchester%20United%20%20Brentford",
        "pubdate": "Sat, 19 Oct 2024 17:00:00 +0200"
    },
    {
        "title": "Bournemouth - Arsenal",
        "link": "https://trends.google.com/trends/trendingsearches/daily?geo=ES#Bournemouth%20-%20Arsenal",
        "pubdate": "Sat, 19 Oct 2024 20:00:00 +0200"
    }
]