[
    {
        "title": "Marcelo",
        "link": "https://trends.google.com/trends/trendingsearches/daily?geo=ES#Marcelo",
        "pubdate": "Tue, 11 Feb 2025 00:00:00 +0100"
    },
    {
        "title": "Nintendo Switch 2 precio",
        "link": "https://trends.google.com/trends/trendingsearches/daily?geo=ES#Nintendo%20Switch%202%20precio",
        "pubdate": "Tue, 11 Feb 2025 01:00:00 +0100"
    },
    {
        "title": "RCD Mallorca - Osasuna",
        "link": "https://trends.google.com/trends/trendingsearches/daily?geo=ES#RCD%20Mallorca%20-%20Osasuna",
        "pubdate": "Mon, 10 Feb 2025 21:00:00 +0100"
    },
    {
        "title": "Barça",
        "link": "https://trends.google.com/trends/trendingsearches/daily?geo=ES#Bar%C3%A7a",
        "pubdate": "Mon, 10 Feb 2025 16:00:00 +0100"
    },
    {
        "title": "Champions League",
        "link": "https://trends.google.com/trends/trendingsearches/daily?geo=ES#Champions%20League",
        "pubdate": "Mon, 10 Feb 2025 19:00:00 +0100"
    },
    {
        "title": "FC Barcelona",
        "link": "https://trends.google.com/trends/trendingsearches/daily?geo=ES#FC%20Barcelona",
        "pubdate": "Mon, 10 Feb 2025 16:00:00 +0100"
    },
    {
        "title": "Real Oviedo  CD Eldense",
        "link": "https://trends.google.com/trends/trendingsearches/daily?geo=ES#Real%20Oviedo%20%20CD%20Eldense",
        "pubdate": "Mon, 10 Feb 2025 20:00:00 +0100"
    },
    {
        "title": "Taylor Swift",
        "link": "https://trends.google.com/trends/trendingsearches/daily?geo=ES#Taylor%20Swift",
        "pubdate": "Mon, 10 Feb 2025 05:00:00 +0100"
    },
    {
        "title": "DAZN",
        "link": "https://trends.google.com/trends/trendingsearches/daily?geo=ES#DAZN",
        "pubdate": "Mon, 10 Feb 2025 01:00:00 +0100"
    },
    {
        "title": "Paula Badosa",
        "link": "https://trends.google.com/trends/trendingsearches/daily?geo=ES#Paula%20Badosa",
        "pubdate": "Mon, 10 Feb 2025 18:00:00 +0100"
    },
    {
        "title": "Febrero Festivos",
        "link": "https://trends.google.com/trends/trendingsearches/daily?geo=ES#Febrero%20Festivos",
        "pubdate": "Mon, 10 Feb 2025 17:00:00 +0100"
    },
    {
        "title": "Inter - Fiorentina",
        "link": "https://trends.google.com/trends/trendingsearches/daily?geo=ES#Inter%20-%20Fiorentina",
        "pubdate": "Mon, 10 Feb 2025 21:00:00 +0100"
    },
    {
        "title": "SMI",
        "link": "https://trends.google.com/trends/trendingsearches/daily?geo=ES#SMI",
        "pubdate": "Mon, 10 Feb 2025 16:00:00 +0100"
    },
    {
        "title": "Elena Tejada",
        "link": "https://trends.google.com/trends/trendingsearches/daily?geo=ES#Elena%20Tejada",
        "pubdate": "Mon, 10 Feb 2025 12:00:00 +0100"
    },
    {
        "title": "Rafael Altamira",
        "link": "https://trends.google.com/trends/trendingsearches/daily?geo=ES#Rafael%20Altamira",
        "pubdate": "Mon, 10 Feb 2025 16:00:00 +0100"
    },
    {
        "title": "La conquista del oeste",
        "link": "https://trends.google.com/trends/trendingsearches/daily?geo=ES#La%20conquista%20del%20oeste",
        "pubdate": "Mon, 10 Feb 2025 23:00:00 +0100"
    },
    {
        "title": "Barcelona vs",
        "link": "https://trends.google.com/trends/trendingsearches/daily?geo=ES#Barcelona%20vs",
        "pubdate": "Mon, 10 Feb 2025 15:00:00 +0100"
    },
    {
        "title": "Raphinha",
        "link": "https://trends.google.com/trends/trendingsearches/daily?geo=ES#Raphinha",
        "pubdate": "Mon, 10 Feb 2025 11:00:00 +0100"
    },
    {
        "title": "Luna llena febrero 2025",
        "link": "https://trends.google.com/trends/trendingsearches/daily?geo=ES#Luna%20llena%20febrero%202025",
        "pubdate": "Mon, 10 Feb 2025 17:00:00 +0100"
    },
    {
        "title": "Reducción jornada laboral",
        "link": "https://trends.google.com/trends/trendingsearches/daily?geo=ES#Reducci%C3%B3n%20jornada%20laboral",
        "pubdate": "Mon, 10 Feb 2025 21:00:00 +0100"
    }
]